README
setup.py
Maki.egg-info/PKG-INFO
Maki.egg-info/SOURCES.txt
Maki.egg-info/dependency_links.txt
Maki.egg-info/top_level.txt
maki/__init__.py