Metadata-Version: 1.0
Name: Maki
Version: 0.0.1
Summary: minimalist functional library
Home-page: https://github.com/phzbox/Maki
Author: phzbOx
Author-email: phzbox@gmail.com
License: WTFPL
Keywords: functional
Platform: UNKNOWN
Classifier: Development Status :: 3 - Alpha
Classifier: Topic :: Utilities
